multiset/__init__.py
multiset/__init__.pyi
multiset/py.typed
multiset-3.2.0.dist-info/LICENSE
multiset-3.2.0.dist-info/METADATA
multiset-3.2.0.dist-info/WHEEL
multiset-3.2.0.dist-info/top_level.txt
multiset-3.2.0.dist-info/zip-safe
multiset-3.2.0.dist-info/RECORD
