Metadata-Version: 2.1
Name: multiset
Version: 3.2.0
Summary: An implementation of a multiset.
Home-page: https://github.com/wheerd/multiset
Author: Manuel Krebber
Author-email: Manuel Krebber <admin@wheerd.de>
License: MIT
Classifier: Development Status :: 5 - Production/Stable
Classifier: Intended Audience :: Developers
Classifier: License :: OSI Approved :: MIT License
Classifier: Programming Language :: Python
Classifier: Programming Language :: Python :: 3
Classifier: Programming Language :: Python :: 3.8
Classifier: Programming Language :: Python :: 3.9
Classifier: Programming Language :: Python :: 3.10
Classifier: Programming Language :: Python :: 3.11
Classifier: Programming Language :: Python :: 3.12
Requires-Python: >=3.8
License-File: LICENSE
